Workbook

Sheet Timesheet
A1: 🕐 EMPLOYEE TIMESHEET & PAYROLL CALCULATOR | 2-Hour Monthly Buffer Enabled
A2: Normal Hours: 8/day | OT Rate: 1.5× | Monthly Short-Hour Buffer: 2 hrs (no deduction)
A4: Emp ID | B4: Employee Name | C4: Department | D4: Date | E4: In Time | F4: Out Time | G4: Total Hrs | H4: Normal Hrs | I4: Short Hrs (Deficit) | J4: OT Hours | K4: Status | L4: Daily Rate ₹ | M4: Daily Pay ₹ | N4: OT Pay ₹
A5: E101 | B5: Rahul Sharma | C5: IT | D5: 01-May-26 | E5: 09:00 | F5: 18:30 | G5: =IFERROR(IF(ISNUMBER(F5),(F5-E5)*24,(TIMEVALUE(F5)-TIMEVALUE(E5))*24),"--") -> 9.5 | H5: =IFERROR(IF(G5="--","--",MIN(G5,8)),"--") -> 8 | I5: =IFERROR(IF(G5="--","--",IF(G5<8,8-G5,0)),"--") -> 0 | J5: =IFERROR(IF(G5="--","--",IF(G5>8,G5-8,0)),"--") -> 1.5 | K5: =IF(G5="--","--",IF(G5>=8,"✅ Present","⚠ Short")) -> ✅ Present | L5: 1200 | M5: =IFERROR(IF(H5="--","--",(H5/8)*L5),"--") -> 1200 | N5: =IFERROR(IF(J5="--","--",J5*(L5/8)*1.5),"--") -> 337.5
A6: E102 | B6: Priya Patel | C6: HR | D6: 02-May-26 | E6: 08:30 | F6: 17:00 | G6: =IFERROR(IF(ISNUMBER(F6),(F6-E6)*24,(TIMEVALUE(F6)-TIMEVALUE(E6))*24),"--") -> 8.5 | H6: =IFERROR(IF(G6="--","--",MIN(G6,8)),"--") -> 8 | I6: =IFERROR(IF(G6="--","--",IF(G6<8,8-G6,0)),"--") -> 0 | J6: =IFERROR(IF(G6="--","--",IF(G6>8,G6-8,0)),"--") -> 0.5 | K6: =IF(G6="--","--",IF(G6>=8,"✅ Present","⚠ Short")) -> ✅ Present | L6: 950 | M6: =IFERROR(IF(H6="--","--",(H6/8)*L6),"--") -> 950 | N6: =IFERROR(IF(J6="--","--",J6*(L6/8)*1.5),"--") -> 89.0625
A7: E103 | B7: Arun Kumar | C7: Finance | D7: 02-May-26 | E7: 09:15 | F7: 19:00 | G7: =IFERROR(IF(ISNUMBER(F7),(F7-E7)*24,(TIMEVALUE(F7)-TIMEVALUE(E7))*24),"--") -> 9.75 | H7: =IFERROR(IF(G7="--","--",MIN(G7,8)),"--") -> 8 | I7: =IFERROR(IF(G7="--","--",IF(G7<8,8-G7,0)),"--") -> 0 | J7: =IFERROR(IF(G7="--","--",IF(G7>8,G7-8,0)),"--") -> 1.75 | K7: =IF(G7="--","--",IF(G7>=8,"✅ Present","⚠ Short")) -> ✅ Present | L7: 1100 | M7: =IFERROR(IF(H7="--","--",(H7/8)*L7),"--") -> 1100 | N7: =IFERROR(IF(J7="--","--",J7*(L7/8)*1.5),"--") -> 360.9375
A8: E101 | B8: Rahul Sharma | C8: IT | D8: 03-May-26 | E8: 08:45 | F8: 17:30 | G8: =IFERROR(IF(ISNUMBER(F8),(F8-E8)*24,(TIMEVALUE(F8)-TIMEVALUE(E8))*24),"--") -> 8.75 | H8: =IFERROR(IF(G8="--","--",MIN(G8,8)),"--") -> 8 | I8: =IFERROR(IF(G8="--","--",IF(G8<8,8-G8,0)),"--") -> 0 | J8: =IFERROR(IF(G8="--","--",IF(G8>8,G8-8,0)),"--") -> 0.75 | K8: =IF(G8="--","--",IF(G8>=8,"✅ Present","⚠ Short")) -> ✅ Present | L8: 1200 | M8: =IFERROR(IF(H8="--","--",(H8/8)*L8),"--") -> 1200 | N8: =IFERROR(IF(J8="--","--",J8*(L8/8)*1.5),"--") -> 168.75
A9: E102 | B9: Priya Patel | C9: HR | D9: 03-May-26 | E9: 09:00 | F9: 18:00 | G9: =IFERROR(IF(ISNUMBER(F9),(F9-E9)*24,(TIMEVALUE(F9)-TIMEVALUE(E9))*24),"--") -> 9 | H9: =IFERROR(IF(G9="--","--",MIN(G9,8)),"--") -> 8 | I9: =IFERROR(IF(G9="--","--",IF(G9<8,8-G9,0)),"--") -> 0 | J9: =IFERROR(IF(G9="--","--",IF(G9>8,G9-8,0)),"--") -> 1 | K9: =IF(G9="--","--",IF(G9>=8,"✅ Present","⚠ Short")) -> ✅ Present | L9: 950 | M9: =IFERROR(IF(H9="--","--",(H9/8)*L9),"--") -> 950 | N9: =IFERROR(IF(J9="--","--",J9*(L9/8)*1.5),"--") -> 178.125
A10: E104 | B10: Sneha Reddy | C10: IT | D10: 03-May-26 | E10: 08:00 | F10: 18:00 | G10: =IFERROR(IF(ISNUMBER(F10),(F10-E10)*24,(TIMEVALUE(F10)-TIMEVALUE(E10))*24),"--") -> 10 | H10: =IFERROR(IF(G10="--","--",MIN(G10,8)),"--") -> 8 | I10: =IFERROR(IF(G10="--","--",IF(G10<8,8-G10,0)),"--") -> 0 | J10: =IFERROR(IF(G10="--","--",IF(G10>8,G10-8,0)),"--") -> 2 | K10: =IF(G10="--","--",IF(G10>=8,"✅ Present","⚠ Short")) -> ✅ Present | L10: 1050 | M10: =IFERROR(IF(H10="--","--",(H10/8)*L10),"--") -> 1050 | N10: =IFERROR(IF(J10="--","--",J10*(L10/8)*1.5),"--") -> 393.75
A11: E103 | B11: Arun Kumar | C11: Finance | D11: 05-May-26 | E11: 09:30 | F11: 17:45 | G11: =IFERROR(IF(ISNUMBER(F11),(F11-E11)*24,(TIMEVALUE(F11)-TIMEVALUE(E11))*24),"--") -> 8.25 | H11: =IFERROR(IF(G11="--","--",MIN(G11,8)),"--") -> 8 | I11: =IFERROR(IF(G11="--","--",IF(G11<8,8-G11,0)),"--") -> 0 | J11: =IFERROR(IF(G11="--","--",IF(G11>8,G11-8,0)),"--") -> 0.25 | K11: =IF(G11="--","--",IF(G11>=8,"✅ Present","⚠ Short")) -> ✅ Present | L11: 1100 | M11: =IFERROR(IF(H11="--","--",(H11/8)*L11),"--") -> 1100 | N11: =IFERROR(IF(J11="--","--",J11*(L11/8)*1.5),"--") -> 51.5625
A12: E101 | B12: Rahul Sharma | C12: IT | D12: 05-May-26 | E12: 08:15 | F12: 20:00 | G12: =IFERROR(IF(ISNUMBER(F12),(F12-E12)*24,(TIMEVALUE(F12)-TIMEVALUE(E12))*24),"--") -> 11.75 | H12: =IFERROR(IF(G12="--","--",MIN(G12,8)),"--") -> 8 | I12: =IFERROR(IF(G12="--","--",IF(G12<8,8-G12,0)),"--") -> 0 | J12: =IFERROR(IF(G12="--","--",IF(G12>8,G12-8,0)),"--") -> 3.75 | K12: =IF(G12="--","--",IF(G12>=8,"✅ Present","⚠ Short")) -> ✅ Present | L12: 1200 | M12: =IFERROR(IF(H12="--","--",(H12/8)*L12),"--") -> 1200 | N12: =IFERROR(IF(J12="--","--",J12*(L12/8)*1.5),"--") -> 843.75
A13: E104 | B13: Sneha Reddy | C13: IT | D13: 06-May-26 | E13: 09:00 | F13: 17:30 | G13: =IFERROR(IF(ISNUMBER(F13),(F13-E13)*24,(TIMEVALUE(F13)-TIMEVALUE(E13))*24),"--") -> 8.5 | H13: =IFERROR(IF(G13="--","--",MIN(G13,8)),"--") -> 8 | I13: =IFERROR(IF(G13="--","--",IF(G13<8,8-G13,0)),"--") -> 0 | J13: =IFERROR(IF(G13="--","--",IF(G13>8,G13-8,0)),"--") -> 0.5 | K13: =IF(G13="--","--",IF(G13>=8,"✅ Present","⚠ Short")) -> ✅ Present | L13: 1050 | M13: =IFERROR(IF(H13="--","--",(H13/8)*L13),"--") -> 1050 | N13: =IFERROR(IF(J13="--","--",J13*(L13/8)*1.5),"--") -> 98.4375
A14: E102 | B14: Priya Patel | C14: HR | D14: 06-May-26 | E14: 08:45 | F14: 18:15 | G14: =IFERROR(IF(ISNUMBER(F14),(F14-E14)*24,(TIMEVALUE(F14)-TIMEVALUE(E14))*24),"--") -> 9.5 | H14: =IFERROR(IF(G14="--","--",MIN(G14,8)),"--") -> 8 | I14: =IFERROR(IF(G14="--","--",IF(G14<8,8-G14,0)),"--") -> 0 | J14: =IFERROR(IF(G14="--","--",IF(G14>8,G14-8,0)),"--") -> 1.5 | K14: =IF(G14="--","--",IF(G14>=8,"✅ Present","⚠ Short")) -> ✅ Present | L14: 950 | M14: =IFERROR(IF(H14="--","--",(H14/8)*L14),"--") -> 950 | N14: =IFERROR(IF(J14="--","--",J14*(L14/8)*1.5),"--") -> 267.1875
A15: E103 | B15: Arun Kumar | C15: Finance | D15: 07-May-26 | E15: 09:00 | F15: 0.66666667 | G15: =IFERROR(IF(ISNUMBER(F15),(F15-E15)*24,(TIMEVALUE(F15)-TIMEVALUE(E15))*24),"--") -> 7 | H15: =IFERROR(IF(G15="--","--",MIN(G15,8)),"--") -> 7 | I15: =IFERROR(IF(G15="--","--",IF(G15<8,8-G15,0)),"--") -> 1 | J15: =IFERROR(IF(G15="--","--",IF(G15>8,G15-8,0)),"--") -> 0 | K15: =IF(G15="--","--",IF(G15>=8,"✅ Present","⚠ Short")) -> ⚠ Short | L15: 1100 | M15: =IFERROR(IF(H15="--","--",(H15/8)*L15),"--") -> 962.5 | N15: =IFERROR(IF(J15="--","--",J15*(L15/8)*1.5),"--") -> 0
A16: E101 | B16: Rahul Sharma | C16: IT | D16: 08-May-26 | E16: 08:30 | F16: 17:00 | G16: =IFERROR(IF(ISNUMBER(F16),(F16-E16)*24,(TIMEVALUE(F16)-TIMEVALUE(E16))*24),"--") -> 8.5 | H16: =IFERROR(IF(G16="--","--",MIN(G16,8)),"--") -> 8 | I16: =IFERROR(IF(G16="--","--",IF(G16<8,8-G16,0)),"--") -> 0 | J16: =IFERROR(IF(G16="--","--",IF(G16>8,G16-8,0)),"--") -> 0.5 | K16: =IF(G16="--","--",IF(G16>=8,"✅ Present","⚠ Short")) -> ✅ Present | L16: 1200 | M16: =IFERROR(IF(H16="--","--",(H16/8)*L16),"--") -> 1200 | N16: =IFERROR(IF(J16="--","--",J16*(L16/8)*1.5),"--") -> 112.5
A17: E104 | B17: Sneha Reddy | C17: IT | D17: 08-May-26 | E17: 08:00 | F17: 18:30 | G17: =IFERROR(IF(ISNUMBER(F17),(F17-E17)*24,(TIMEVALUE(F17)-TIMEVALUE(E17))*24),"--") -> 10.5 | H17: =IFERROR(IF(G17="--","--",MIN(G17,8)),"--") -> 8 | I17: =IFERROR(IF(G17="--","--",IF(G17<8,8-G17,0)),"--") -> 0 | J17: =IFERROR(IF(G17="--","--",IF(G17>8,G17-8,0)),"--") -> 2.5 | K17: =IF(G17="--","--",IF(G17>=8,"✅ Present","⚠ Short")) -> ✅ Present | L17: 1050 | M17: =IFERROR(IF(H17="--","--",(H17/8)*L17),"--") -> 1050 | N17: =IFERROR(IF(J17="--","--",J17*(L17/8)*1.5),"--") -> 492.1875
A18: E102 | B18: Priya Patel | C18: HR | D18: 09-May-26 | E18: 09:15 | F18: 17:45 | G18: =IFERROR(IF(ISNUMBER(F18),(F18-E18)*24,(TIMEVALUE(F18)-TIMEVALUE(E18))*24),"--") -> 8.5 | H18: =IFERROR(IF(G18="--","--",MIN(G18,8)),"--") -> 8 | I18: =IFERROR(IF(G18="--","--",IF(G18<8,8-G18,0)),"--") -> 0 | J18: =IFERROR(IF(G18="--","--",IF(G18>8,G18-8,0)),"--") -> 0.5 | K18: =IF(G18="--","--",IF(G18>=8,"✅ Present","⚠ Short")) -> ✅ Present | L18: 950 | M18: =IFERROR(IF(H18="--","--",(H18/8)*L18),"--") -> 950 | N18: =IFERROR(IF(J18="--","--",J18*(L18/8)*1.5),"--") -> 89.0625
A19: E103 | B19: Arun Kumar | C19: Finance | D19: 09-May-26 | E19: 09:00 | F19: 0.625 | G19: =IFERROR(IF(ISNUMBER(F19),(F19-E19)*24,(TIMEVALUE(F19)-TIMEVALUE(E19))*24),"--") -> 6 | H19: =IFERROR(IF(G19="--","--",MIN(G19,8)),"--") -> 6 | I19: =IFERROR(IF(G19="--","--",IF(G19<8,8-G19,0)),"--") -> 2 | J19: =IFERROR(IF(G19="--","--",IF(G19>8,G19-8,0)),"--") -> 0 | K19: =IF(G19="--","--",IF(G19>=8,"✅ Present","⚠ Short")) -> ⚠ Short | L19: 1100 | M19: =IFERROR(IF(H19="--","--",(H19/8)*L19),"--") -> 825 | N19: =IFERROR(IF(J19="--","--",J19*(L19/8)*1.5),"--") -> 0
A22: 📊 EMPLOYEE MONTHLY SUMMARY — 2-Hour Buffer Applied
A23: Emp ID | B23: Name | C23: Days Worked (COUNTIF) | D23: Total Short Hrs (SUMIF) | E23: Buffer (2 hrs) | F23: Deductible Short Hrs | G23: Deduction ₹ (Short Hrs) | H23: Total OT Hrs (SUMIF) | I23: Gross Pay ₹ (SUMIF) | J23: OT Pay ₹ (SUMIF) | K23: Buffer Saving ₹ | L23: Net Pay ₹
A24: E101 | B24: Rahul Sharma | C24: =COUNTIF($A$5:$A$19,A24) -> 4 | D24: =IFERROR(SUMIF($A$5:$A$19,A24,$I$5:$I$19),0) -> 0 | E24: 2.00 | F24: =MAX(0,D24-E24) -> 0 | G24: =IFERROR(F24*(SUMIF($A$5:$A$19,A24,$L$5:$L$19)/COUNTIF($A$5:$A$19,A24))/8,0) -> 0 | H24: =IFERROR(SUMIF($A$5:$A$19,A24,$J$5:$J$19),0) -> 6.5 | I24: =IFERROR(SUMIF($A$5:$A$19,A24,$M$5:$M$19),0) -> 4800 | J24: =IFERROR(SUMIF($A$5:$A$19,A24,$N$5:$N$19),0) -> 1462.5 | K24: =IFERROR(MIN(D24,2)*(SUMIF($A$5:$A$19,A24,$L$5:$L$19)/COUNTIF($A$5:$A$19,A24))/8,0) -> 0 | L24: =I24+J24-G24 -> 6262.5
A25: E102 | B25: Priya Patel | C25: =COUNTIF($A$5:$A$19,A25) -> 4 | D25: =IFERROR(SUMIF($A$5:$A$19,A25,$I$5:$I$19),0) -> 0 | E25: 2.00 | F25: =MAX(0,D25-E25) -> 0 | G25: =IFERROR(F25*(SUMIF($A$5:$A$19,A25,$L$5:$L$19)/COUNTIF($A$5:$A$19,A25))/8,0) -> 0 | H25: =IFERROR(SUMIF($A$5:$A$19,A25,$J$5:$J$19),0) -> 3.5 | I25: =IFERROR(SUMIF($A$5:$A$19,A25,$M$5:$M$19),0) -> 3800 | J25: =IFERROR(SUMIF($A$5:$A$19,A25,$N$5:$N$19),0) -> 623.4375 | K25: =IFERROR(MIN(D25,2)*(SUMIF($A$5:$A$19,A25,$L$5:$L$19)/COUNTIF($A$5:$A$19,A25))/8,0) -> 0 | L25: =I25+J25-G25 -> 4423.4375
A26: E103 | B26: Arun Kumar | C26: =COUNTIF($A$5:$A$19,A26) -> 4 | D26: =IFERROR(SUMIF($A$5:$A$19,A26,$I$5:$I$19),0) -> 3 | E26: 2.00 | F26: =MAX(0,D26-E26) -> 1 | G26: =IFERROR(F26*(SUMIF($A$5:$A$19,A26,$L$5:$L$19)/COUNTIF($A$5:$A$19,A26))/8,0) -> 137.5 | H26: =IFERROR(SUMIF($A$5:$A$19,A26,$J$5:$J$19),0) -> 2 | I26: =IFERROR(SUMIF($A$5:$A$19,A26,$M$5:$M$19),0) -> 3987.5 | J26: =IFERROR(SUMIF($A$5:$A$19,A26,$N$5:$N$19),0) -> 412.5 | K26: =IFERROR(MIN(D26,2)*(SUMIF($A$5:$A$19,A26,$L$5:$L$19)/COUNTIF($A$5:$A$19,A26))/8,0) -> 275 | L26: =I26+J26-G26 -> 4262.5
A27: E104 | B27: Sneha Reddy | C27: =COUNTIF($A$5:$A$19,A27) -> 3 | D27: =IFERROR(SUMIF($A$5:$A$19,A27,$I$5:$I$19),0) -> 0 | E27: 2.00 | F27: =MAX(0,D27-E27) -> 0 | G27: =IFERROR(F27*(SUMIF($A$5:$A$19,A27,$L$5:$L$19)/COUNTIF($A$5:$A$19,A27))/8,0) -> 0 | H27: =IFERROR(SUMIF($A$5:$A$19,A27,$J$5:$J$19),0) -> 5 | I27: =IFERROR(SUMIF($A$5:$A$19,A27,$M$5:$M$19),0) -> 3150 | J27: =IFERROR(SUMIF($A$5:$A$19,A27,$N$5:$N$19),0) -> 984.375 | K27: =IFERROR(MIN(D27,2)*(SUMIF($A$5:$A$19,A27,$L$5:$L$19)/COUNTIF($A$5:$A$19,A27))/8,0) -> 0 | L27: =I27+J27-G27 -> 4134.375
A30: ℹ️ BUFFER RULE: Each employee gets 2 hrs/month grace. Short hrs ≤ 2 → No deduction. Short hrs > 2 → Only excess hours are deducted from salary.

Sheet Payroll Calculator
A1: 💰 MONTHLY PAYROLL CALCULATOR — 2-Hour Buffer Rule Active
A2: Payroll Period: May 2026 | Buffer: 2 hrs/employee/month | PF Deduction: 10%
A4: Emp ID | B4: Name | C4: Dept | D4: Days Worked | E4: Gross Pay ₹ | F4: OT Pay ₹ | G4: Short Hr Deduction ₹ | H4: Buffer Saving ₹ | I4: PF (10%) ₹ | J4: Net Salary ₹
A5: E101 | B5: Rahul Sharma | C5: IT | D5: =Timesheet!C24 -> 4 | E5: =Timesheet!I24 -> 4800 | F5: =Timesheet!J24 -> 1462.5 | G5: =Timesheet!G24 -> 0 | H5: =Timesheet!K24 -> 0 | I5: =(E5+F5-G5)*0.1 -> 626.25 | J5: =E5+F5-G5-I5 -> 5636.25
A6: E102 | B6: Priya Patel | C6: HR | D6: =Timesheet!C25 -> 4 | E6: =Timesheet!I25 -> 3800 | F6: =Timesheet!J25 -> 623.4375 | G6: =Timesheet!G25 -> 0 | H6: =Timesheet!K25 -> 0 | I6: =(E6+F6-G6)*0.1 -> 442.34375 | J6: =E6+F6-G6-I6 -> 3981.0938
A7: E103 | B7: Arun Kumar | C7: Finance | D7: =Timesheet!C26 -> 4 | E7: =Timesheet!I26 -> 3987.5 | F7: =Timesheet!J26 -> 412.5 | G7: =Timesheet!G26 -> 137.5 | H7: =Timesheet!K26 -> 275 | I7: =(E7+F7-G7)*0.1 -> 426.25 | J7: =E7+F7-G7-I7 -> 3836.25
A8: E104 | B8: Sneha Reddy | C8: IT | D8: =Timesheet!C27 -> 3 | E8: =Timesheet!I27 -> 3150 | F8: =Timesheet!J27 -> 984.375 | G8: =Timesheet!G27 -> 0 | H8: =Timesheet!K27 -> 0 | I8: =(E8+F8-G8)*0.1 -> 413.4375 | J8: =E8+F8-G8-I8 -> 3720.9375
A9: TOTAL | E9: =SUM(E5:E8) -> 15737.5 | F9: =SUM(F5:F8) -> 3482.8125 | G9: =SUM(G5:G8) -> 137.5 | H9: =SUM(H5:H8) -> 275 | I9: =SUM(I5:I8) -> 1908.2812 | J9: =SUM(J5:J8) -> 17174.531
A12: ⚙ HOW THE 2-HOUR BUFFER WORKS
A13: Rule | B13: Each employee gets a 2-hour monthly buffer for short working days
A14: If Short Hrs ≤ 2 hrs | B14: → No salary deduction at all ✅
A15: If Short Hrs > 2 hrs | B15: → Only the EXCESS hours (beyond 2) are deducted ⚠
A16: Example | B16: Worked 7 hrs on 1 day (1 hr short) → within buffer → Full pay
A17: Example | B17: Worked 6 hrs on 1 day + 6.5 hrs another (2.5 hrs short total) → 0.5 hrs deducted
A18: Buffer Saving ₹ | B18: Shows how much money was SAVED for the employee due to the buffer

Sheet Salary Slip
B1: 🏢 COMPANY NAME PVT. LTD.
B2: SALARY SLIP | Month: May 2026
B4: ℹ️ Change the Emp ID in cell C5 to auto-load that employee's payroll data
B5: Employee ID | C5: E103 | D5: Department | E5: IT
B6: Employee Name | C6: ARUN KUMAR | D6: Designation | E6: Software Engineer
B7: Pay Period | C7: May 2026 | D7: Working Days | E7: =IFERROR(INDEX('Payroll Calculator'!D5:D8,MATCH(C5,'Payroll Calculator'!A5:A8,0)),"--") -> 4
B8: Bank Account | C8: XXXX-XXXX-1234 | D8: IFSC Code | E8: SBIN0001234
B9: Payment Mode | C9: Bank Transfer | D9: PF Account | E9: KA/BNG/12345
B11: EARNINGS | D11: DEDUCTIONS
B12: Component | C12: Amount (₹) | D12: Component | E12: Amount (₹)
B13: Basic / Daily Pay | C13: =IFERROR(INDEX('Payroll Calculator'!E5:E8,MATCH(C5,'Payroll Calculator'!A5:A8,0)),0) -> 3987.5 | D13: Short Hr Deduction | E13: =IFERROR(INDEX('Payroll Calculator'!G5:G8,MATCH(C5,'Payroll Calculator'!A5:A8,0)),0) -> 137.5
B14: Overtime Pay | C14: =IFERROR(INDEX('Payroll Calculator'!F5:F8,MATCH(C5,'Payroll Calculator'!A5:A8,0)),0) -> 412.5 | D14: Provident Fund (PF) | E14: =IFERROR(INDEX('Payroll Calculator'!I5:I8,MATCH(C5,'Payroll Calculator'!A5:A8,0)),0) -> 426.25
B15: Attendance Bonus | C15: 200 | D15: Professional Tax | E15: 150
B17: Gross Earnings | C17: =SUM(C13:C16) -> 4600 | D17: Total Deductions | E17: =SUM(E13:E16) -> 713.75
B19: ="✅ 2-Hr Buffer Saving this month: ₹"&TEXT(IFERROR(INDEX('Payroll Calculator'!H5:H8,MATCH(C5,'Payroll Calculator'!A5:A8,0)),0),"#,##0.00")&" — No deduction applied for hours within buffer" -> ✅ 2-Hr Buffer Saving this month: ₹275.00 — No deduction applied for hours within buffer
B21: =IFERROR("NET SALARY PAYABLE: ₹"&TEXT(INDEX('Payroll Calculator'!J5:J8,MATCH(C5,'Payroll Calculator'!A5:A8,0)),"#,##0.00"),"NET SALARY PAYABLE: ₹0.00") -> NET SALARY PAYABLE: ₹3,836.25
B23: Employee Signature | D23: Authorized Signatory
B25: This is a computer-generated payslip. The 2-hour monthly buffer has been applied as per company policy.
