Workbook

Sheet Timesheet
A1: 🕐 EMPLOYEE TIMESHEET & PAYROLL CALCULATOR
A2: Month: May 2026 | Normal Hours: 8/day | OT Rate: 1.5×
A4: Emp ID | B4: Employee Name | C4: Department | D4: Date | E4: In Time | F4: Out Time | G4: Total Hrs | H4: Normal Hrs | I4: OT Hours | J4: Status | K4: Daily Rate (₹) | L4: Daily Pay (₹) | M4: OT Pay (₹)
A5: E101 | B5: Rahul Sharma | C5: IT | D5: 46143 | E5: 09:00 | F5: 18:30 | G5: =IFERROR((TIMEVALUE(F5)-TIMEVALUE(E5))*24,"--") -> 9.5 | H5: =IFERROR(MIN(G5,8),"--") -> 8 | I5: =IFERROR(IF(G5>8,G5-8,0),"--") -> 1.5 | J5: =IF(G5>=8,"✅ Present","⚠ Short") -> ✅ Present | K5: 1200 | L5: =IFERROR((H5/8)*K5,"--") -> 1200 | M5: =IFERROR(I5*(K5/8)*1.5,"--") -> 337.5
A6: E102 | B6: Priya Patel | C6: HR | D6: 02-May-26 | E6: 08:30 | F6: 17:00 | G6: =IFERROR((TIMEVALUE(F6)-TIMEVALUE(E6))*24,"--") -> 8.5 | H6: =IFERROR(MIN(G6,8),"--") -> 8 | I6: =IFERROR(IF(G6>8,G6-8,0),"--") -> 0.5 | J6: =IF(G6>=8,"✅ Present","⚠ Short") -> ✅ Present | K6: 950 | L6: =IFERROR((H6/8)*K6,"--") -> 950 | M6: =IFERROR(I6*(K6/8)*1.5,"--") -> 89.0625
A7: E103 | B7: Arun Kumar | C7: Finance | D7: 02-May-26 | E7: 09:15 | F7: 19:00 | G7: =IFERROR((TIMEVALUE(F7)-TIMEVALUE(E7))*24,"--") -> 9.75 | H7: =IFERROR(MIN(G7,8),"--") -> 8 | I7: =IFERROR(IF(G7>8,G7-8,0),"--") -> 1.75 | J7: =IF(G7>=8,"✅ Present","⚠ Short") -> ✅ Present | K7: 1100 | L7: =IFERROR((H7/8)*K7,"--") -> 1100 | M7: =IFERROR(I7*(K7/8)*1.5,"--") -> 360.9375
A8: E101 | B8: Rahul Sharma | C8: IT | D8: 46144 | E8: 08:00 | F8: 18:00 | G8: =IFERROR((TIMEVALUE(F8)-TIMEVALUE(E8))*24,"--") -> 10 | H8: =IFERROR(MIN(G8,8),"--") -> 8 | I8: =IFERROR(IF(G8>8,G8-8,0),"--") -> 2 | J8: =IF(G8>=8,"✅ Present","⚠ Short") -> ✅ Present | K8: 1101 | L8: =IFERROR((H8/8)*K8,"--") -> 1101 | M8: =IFERROR(I8*(K8/8)*1.5,"--") -> 412.875
A9: E102 | B9: Priya Patel | C9: HR | D9: 03-May-26 | E9: 09:00 | F9: 18:00 | G9: =IFERROR((TIMEVALUE(F9)-TIMEVALUE(E9))*24,"--") -> 9 | H9: =IFERROR(MIN(G9,8),"--") -> 8 | I9: =IFERROR(IF(G9>8,G9-8,0),"--") -> 1 | J9: =IF(G9>=8,"✅ Present","⚠ Short") -> ✅ Present | K9: 950 | L9: =IFERROR((H9/8)*K9,"--") -> 950 | M9: =IFERROR(I9*(K9/8)*1.5,"--") -> 178.125
A10: E104 | B10: Sneha Reddy | C10: IT | D10: 03-May-26 | E10: 08:00 | F10: 18:00 | G10: =IFERROR((TIMEVALUE(F10)-TIMEVALUE(E10))*24,"--") -> 10 | H10: =IFERROR(MIN(G10,8),"--") -> 8 | I10: =IFERROR(IF(G10>8,G10-8,0),"--") -> 2 | J10: =IF(G10>=8,"✅ Present","⚠ Short") -> ✅ Present | K10: 1050 | L10: =IFERROR((H10/8)*K10,"--") -> 1050 | M10: =IFERROR(I10*(K10/8)*1.5,"--") -> 393.75
A11: E103 | B11: Arun Kumar | C11: Finance | D11: 05-May-26 | E11: 09:30 | F11: 17:45 | G11: =IFERROR((TIMEVALUE(F11)-TIMEVALUE(E11))*24,"--") -> 8.25 | H11: =IFERROR(MIN(G11,8),"--") -> 8 | I11: =IFERROR(IF(G11>8,G11-8,0),"--") -> 0.25 | J11: =IF(G11>=8,"✅ Present","⚠ Short") -> ✅ Present | K11: 1100 | L11: =IFERROR((H11/8)*K11,"--") -> 1100 | M11: =IFERROR(I11*(K11/8)*1.5,"--") -> 51.5625
A12: E101 | B12: Rahul Sharma | C12: IT | D12: 05-May-26 | E12: 09:00 | F12: 20:00 | G12: =IFERROR((TIMEVALUE(F12)-TIMEVALUE(E12))*24,"--") -> 11 | H12: =IFERROR(MIN(G12,8),"--") -> 8 | I12: =IFERROR(IF(G12>8,G12-8,0),"--") -> 3 | J12: =IF(G12>=8,"✅ Present","⚠ Short") -> ✅ Present | K12: 1101 | L12: =IFERROR((H12/8)*K12,"--") -> 1101 | M12: =IFERROR(I12*(K12/8)*1.5,"--") -> 619.3125
A13: E104 | B13: Sneha Reddy | C13: IT | D13: 06-May-26 | E13: 09:00 | F13: 17:30 | G13: =IFERROR((TIMEVALUE(F13)-TIMEVALUE(E13))*24,"--") -> 8.5 | H13: =IFERROR(MIN(G13,8),"--") -> 8 | I13: =IFERROR(IF(G13>8,G13-8,0),"--") -> 0.5 | J13: =IF(G13>=8,"✅ Present","⚠ Short") -> ✅ Present | K13: 1050 | L13: =IFERROR((H13/8)*K13,"--") -> 1050 | M13: =IFERROR(I13*(K13/8)*1.5,"--") -> 98.4375
A14: E102 | B14: Priya Patel | C14: HR | D14: 06-May-26 | E14: 08:00 | F14: 18:30 | G14: =IFERROR((TIMEVALUE(F14)-TIMEVALUE(E14))*24,"--") -> 10.5 | H14: =IFERROR(MIN(G14,8),"--") -> 8 | I14: =IFERROR(IF(G14>8,G14-8,0),"--") -> 2.5 | J14: =IF(G14>=8,"✅ Present","⚠ Short") -> ✅ Present | K14: 1051 | L14: 1051 | M14: =IFERROR(I14*(K14/8)*1.5,"--") -> 492.65625
A15: E103 | B15: Arun Kumar | C15: Finance | D15: 07-May-26 | E15: 09:00 | F15: 18:30 | G15: =IFERROR((TIMEVALUE(F15)-TIMEVALUE(E15))*24,"--") -> 9.5 | H15: =IFERROR(MIN(G15,8),"--") -> 8 | I15: =IFERROR(IF(G15>8,G15-8,0),"--") -> 1.5 | J15: =IF(G15>=8,"✅ Present","⚠ Short") -> ✅ Present | K15: 1051 | L15: 1051 | M15: =IFERROR(I15*(K15/8)*1.5,"--") -> 295.59375
A16: E101 | B16: Rahul Sharma | C16: IT | D16: 08-May-26 | E16: 08:30 | F16: 17:00 | G16: =IFERROR((TIMEVALUE(F16)-TIMEVALUE(E16))*24,"--") -> 8.5 | H16: =IFERROR(MIN(G16,8),"--") -> 8 | I16: =IFERROR(IF(G16>8,G16-8,0),"--") -> 0.5 | J16: =IF(G16>=8,"✅ Present","⚠ Short") -> ✅ Present | K16: 1200 | L16: =IFERROR((H16/8)*K16,"--") -> 1200 | M16: =IFERROR(I16*(K16/8)*1.5,"--") -> 112.5
A17: E104 | B17: Sneha Reddy | C17: IT | D17: 08-May-26 | E17: 08:00 | F17: 18:30 | G17: =IFERROR((TIMEVALUE(F17)-TIMEVALUE(E17))*24,"--") -> 10.5 | H17: =IFERROR(MIN(G17,8),"--") -> 8 | I17: =IFERROR(IF(G17>8,G17-8,0),"--") -> 2.5 | J17: =IF(G17>=8,"✅ Present","⚠ Short") -> ✅ Present | K17: 1050 | L17: =IFERROR((H17/8)*K17,"--") -> 1050 | M17: =IFERROR(I17*(K17/8)*1.5,"--") -> 492.1875
A18: E102 | B18: Priya Patel | C18: HR | D18: 09-May-26 | E18: 09:15 | F18: 17:45 | G18: =IFERROR((TIMEVALUE(F18)-TIMEVALUE(E18))*24,"--") -> 8.5 | H18: =IFERROR(MIN(G18,8),"--") -> 8 | I18: =IFERROR(IF(G18>8,G18-8,0),"--") -> 0.5 | J18: =IF(G18>=8,"✅ Present","⚠ Short") -> ✅ Present | K18: 950 | L18: =IFERROR((H18/8)*K18,"--") -> 950 | M18: =IFERROR(I18*(K18/8)*1.5,"--") -> 89.0625
A19: E103 | B19: Arun Kumar | C19: Finance | D19: 09-May-26 | E19: 09:00 | F19: 18:00 | G19: =IFERROR((TIMEVALUE(F19)-TIMEVALUE(E19))*24,"--") -> 9 | H19: =IFERROR(MIN(G19,8),"--") -> 8 | I19: =IFERROR(IF(G19>8,G19-8,0),"--") -> 1 | J19: =IF(G19>=8,"✅ Present","⚠ Short") -> ✅ Present | K19: 1100 | L19: =IFERROR((H19/8)*K19,"--") -> 1100 | M19: =IFERROR(I19*(K19/8)*1.5,"--") -> 206.25
A22: 📊 EMPLOYEE SUMMARY (SUMIF & COUNTIF)
A23: Emp ID | B23: Name | C23: Days Worked (COUNTIF) | D23: Total OT Hrs (SUMIF) | E23: Total Daily Pay ₹ (SUMIF) | F23: Total OT Pay ₹ (SUMIF) | G23: Grand Total ₹
A24: E101 | B24: Rahul Sharma | C24: =COUNTIF($A$5:$A$19,A24) -> 4 | D24: =SUMIF($A$5:$A$19,A24,$I$5:$I$19) -> 7 | E24: =SUMIF($A$5:$A$19,A24,$L$5:$L$19) -> 4602 | F24: =SUMIF($A$5:$A$19,A24,$M$5:$M$19) -> 1482.1875 | G24: =E24+F24 -> 6084.1875
A25: E102 | B25: Priya Patel | C25: =COUNTIF($A$5:$A$19,A25) -> 4 | D25: =SUMIF($A$5:$A$19,A25,$I$5:$I$19) -> 4.5 | E25: =SUMIF($A$5:$A$19,A25,$L$5:$L$19) -> 3901 | F25: =SUMIF($A$5:$A$19,A25,$M$5:$M$19) -> 848.90625 | G25: =E25+F25 -> 4749.9062
A26: E103 | B26: Arun Kumar | C26: =COUNTIF($A$5:$A$19,A26) -> 4 | D26: =SUMIF($A$5:$A$19,A26,$I$5:$I$19) -> 4.5 | E26: =SUMIF($A$5:$A$19,A26,$L$5:$L$19) -> 4351 | F26: =SUMIF($A$5:$A$19,A26,$M$5:$M$19) -> 914.34375 | G26: =E26+F26 -> 5265.3438
A27: E104 | B27: Sneha Reddy | C27: =COUNTIF($A$5:$A$19,A27) -> 3 | D27: =SUMIF($A$5:$A$19,A27,$I$5:$I$19) -> 5 | E27: =SUMIF($A$5:$A$19,A27,$L$5:$L$19) -> 3150 | F27: =SUMIF($A$5:$A$19,A27,$M$5:$M$19) -> 984.375 | G27: =E27+F27 -> 4134.375

Sheet Payroll Calculator
A1: 💰 MONTHLY PAYROLL CALCULATOR
A2: Payroll Period: May 2026 | Currency: INR (₹) | OT Multiplier: 1.5×
A4: Emp ID | B4: Name | C4: Department | D4: Days Worked | E4: Basic Pay ₹ | F4: OT Hours | G4: OT Pay ₹ | H4: Deductions ₹ | I4: Net Salary ₹ | J4: Pay Grade
A5: E101 | B5: Rahul Sharma | C5: IT | D5: =COUNTIF(Timesheet!$A$5:$A$19,A5) -> 4 | E5: =SUMIF(Timesheet!$A$5:$A$19,A5,Timesheet!$L$5:$L$19) -> 4602 | F5: =SUMIF(Timesheet!$A$5:$A$19,A5,Timesheet!$I$5:$I$19) -> 7 | G5: =SUMIF(Timesheet!$A$5:$A$19,A5,Timesheet!$M$5:$M$19) -> 1482.1875 | H5: =E5*0.1 -> 460.2 | I5: =E5+G5-H5 -> 5623.9875 | J5: =IF(I5>=5000,"A - Senior",IF(I5>=3500,"B - Mid","C - Junior")) -> A - Senior
A6: E102 | B6: Priya Patel | C6: HR | D6: =COUNTIF(Timesheet!$A$5:$A$19,A6) -> 4 | E6: =SUMIF(Timesheet!$A$5:$A$19,A6,Timesheet!$L$5:$L$19) -> 3901 | F6: =SUMIF(Timesheet!$A$5:$A$19,A6,Timesheet!$I$5:$I$19) -> 4.5 | G6: =SUMIF(Timesheet!$A$5:$A$19,A6,Timesheet!$M$5:$M$19) -> 848.90625 | H6: =E6*0.1 -> 390.1 | I6: =E6+G6-H6 -> 4359.8062 | J6: =IF(I6>=5000,"A - Senior",IF(I6>=3500,"B - Mid","C - Junior")) -> B - Mid
A7: E103 | B7: Arun Kumar | C7: Finance | D7: =COUNTIF(Timesheet!$A$5:$A$19,A7) -> 4 | E7: =SUMIF(Timesheet!$A$5:$A$19,A7,Timesheet!$L$5:$L$19) -> 4351 | F7: =SUMIF(Timesheet!$A$5:$A$19,A7,Timesheet!$I$5:$I$19) -> 4.5 | G7: =SUMIF(Timesheet!$A$5:$A$19,A7,Timesheet!$M$5:$M$19) -> 914.34375 | H7: =E7*0.1 -> 435.1 | I7: =E7+G7-H7 -> 4830.2437 | J7: =IF(I7>=5000,"A - Senior",IF(I7>=3500,"B - Mid","C - Junior")) -> B - Mid
A8: E104 | B8: Sneha Reddy | C8: IT | D8: =COUNTIF(Timesheet!$A$5:$A$19,A8) -> 3 | E8: =SUMIF(Timesheet!$A$5:$A$19,A8,Timesheet!$L$5:$L$19) -> 3150 | F8: =SUMIF(Timesheet!$A$5:$A$19,A8,Timesheet!$I$5:$I$19) -> 5 | G8: =SUMIF(Timesheet!$A$5:$A$19,A8,Timesheet!$M$5:$M$19) -> 984.375 | H8: =E8*0.1 -> 315 | I8: =E8+G8-H8 -> 3819.375 | J8: =IF(I8>=5000,"A - Senior",IF(I8>=3500,"B - Mid","C - Junior")) -> B - Mid
A9: TOTAL | E9: =SUM(E5:E8) -> 16004 | G9: =SUM(G5:G8) -> 4229.8125 | H9: =SUM(H5:H8) -> 1600.4 | I9: =SUM(I5:I8) -> 18633.412
A12: ⚙ PAYROLL ASSUMPTIONS
A13: Normal Work Hours/Day | B13: 8
A14: OT Multiplier | B14: 1.5×
A15: PF Deduction Rate | B15: 10%
A16: Pay Period | B16: Monthly

Sheet Salary Slip
B2: 👤 Select Employee: | D2: E101 - Rahul Sharma
B4: 🏢 PAYROLL MANAGEMENT SYSTEM
B5: EMPLOYEE SALARY SLIP — May 2026
B7: Employee ID | C7: =LEFT(D2,4) -> E101 | D7: Department | E7: =IFERROR(VLOOKUP(LEFT(D2,4),'Payroll Calculator'!$A$5:$J$8,3,0),"") -> IT
B8: Employee Name | C8: =IFERROR(VLOOKUP(LEFT(D2,4),'Payroll Calculator'!$A$5:$J$8,2,0),"") -> Rahul Sharma | D8: Pay Grade | E8: =IFERROR(VLOOKUP(LEFT(D2,4),'Payroll Calculator'!$A$5:$J$8,10,0),"") -> A - Senior
B9: Pay Period | C9: May 2026 | D9: Payment Mode | E9: Bank Transfer
B10: Days Worked | C10: =IFERROR(VLOOKUP(LEFT(D2,4),'Payroll Calculator'!$A$5:$J$8,4,0),"") -> 4 | D10: OT Hours | E10: =IFERROR(VLOOKUP(LEFT(D2,4),'Payroll Calculator'!$A$5:$J$8,6,0),"") -> 7
B12: EARNINGS | D12: DEDUCTIONS
B13: Basic Pay | C13: =IFERROR(VLOOKUP(LEFT(D2,4),'Payroll Calculator'!$A$5:$J$8,5,0),0) -> 4602 | D13: Provident Fund (PF) | E13: =IFERROR(VLOOKUP(LEFT(D2,4),'Payroll Calculator'!$A$5:$J$8,8,0)*0.9,0) -> 414.18
B14: OT Pay | C14: =IFERROR(VLOOKUP(LEFT(D2,4),'Payroll Calculator'!$A$5:$J$8,7,0),0) -> 1482.1875 | D14: Professional Tax | E14: =IFERROR(VLOOKUP(LEFT(D2,4),'Payroll Calculator'!$A$5:$J$8,8,0)*0.1,0) -> 46.02
B15: Attendance Bonus | C15: =IFERROR(IF(VLOOKUP(LEFT(D2,4),'Payroll Calculator'!$A$5:$J$8,4,0)>=4,200,100),0) -> 200
B17: Gross Earnings: | C17: =C13+C14+C15 -> 6284.1875 | D17: Total Deductions: | E17: =E13+E14 -> 460.2
B19: =IFERROR("✅ NET SALARY PAYABLE: ₹"&TEXT(C17-E17,"#,##0.00"),"—") -> ✅ NET SALARY PAYABLE: ₹5,823.99
B21: This is a computer-generated payslip and does not require a physical signature.
B22: ⚠ Change the dropdown above to view salary slips for other employees
